surfaces_onnx_files/__init__.py
surfaces_onnx_files/gradient_boosting_regressor.onnx
surfaces_onnx_files/gradient_boosting_regressor.onnx.meta.json
surfaces_onnx_files/k_neighbors_classifier.onnx
surfaces_onnx_files/k_neighbors_classifier.onnx.meta.json
surfaces_onnx_files/k_neighbors_classifier.validity.onnx
surfaces_onnx_files/k_neighbors_regressor.onnx
surfaces_onnx_files/k_neighbors_regressor.onnx.meta.json
surfaces_onnx_files-0.0.1.dist-info/METADATA
surfaces_onnx_files-0.0.1.dist-info/WHEEL
surfaces_onnx_files-0.0.1.dist-info/top_level.txt
surfaces_onnx_files-0.0.1.dist-info/RECORD
