Metadata-Version: 2.4
Name: surfaces-onnx-files
Version: 0.0.1
Summary: Pre-trained ONNX surrogate models for the surfaces library
Author-email: Simon Blanke <simon.blanke@yahoo.com>
License: MIT
Project-URL: Homepage, https://github.com/SimonBlanke/Surfaces
Project-URL: Repository, https://github.com/SimonBlanke/Surfaces
Classifier: Development Status :: 4 - Beta
Classifier: Intended Audience :: Science/Research
Classifier: Programming Language :: Python :: 3
Classifier: Programming Language :: Python :: 3.8
Classifier: Programming Language :: Python :: 3.9
Classifier: Programming Language :: Python :: 3.10
Classifier: Programming Language :: Python :: 3.11
Classifier: Programming Language :: Python :: 3.12
Classifier: Topic :: Scientific/Engineering :: Artificial Intelligence
Requires-Python: >=3.8
